motify_music-1.0.6.dist-info/METADATA
motify_music-1.0.6.dist-info/WHEEL
motify_music-1.0.6.dist-info/entry_points.txt
motify_music-1.0.6.dist-info/licenses/LICENSE
services/__init__.py
services/downloader.py
services/spotify_service.py
ui/__init__.py
ui/history_tab.py
ui/lyrics_tab.py
ui/main_window.py
ui/queue_tab.py
ui/search_tab.py
ui/settings_tab.py
ui/stats_tab.py
ui/youtube_tab.py
utils/__init__.py
utils/config.py
utils/ui_styles.py
motify_music-1.0.6.dist-info/RECORD
