Metadata-Version: 2.1
Name: motify-music
Version: 1.0.6
Summary: A modern Python-based Spotify Music Downloader with a beautiful GUI, playlist management, and high-quality audio support
Keywords: spotify,music,downloader,gui,audio,playlist,yt-dlp,lyrics,manager
Author-Email: Mosh3eb <Mosh2eb@gmail.com>
License: MIT
Classifier: Development Status :: 5 - Production/Stable
Classifier: Intended Audience :: End Users/Desktop
Classifier: Operating System :: OS Independent
Classifier: Programming Language :: Python :: 3
Classifier: Programming Language :: Python :: 3.10
Classifier: Programming Language :: Python :: 3.11
Classifier: Programming Language :: Python :: 3.12
Classifier: Topic :: Multimedia :: Sound/Audio
Classifier: License :: OSI Approved :: MIT License
Project-URL: Homepage, https://motify-music.netlify.app
Project-URL: Documentation, https://motify-music.netlify.app
Project-URL: Repository, https://github.com/mosh3eb/motify.git
Project-URL: Bug Tracker, https://github.com/mosh3eb/motify/issues
Project-URL: Changelog, https://motify-music.netlify.app/changelog
Requires-Python: >=3.10
Requires-Dist: requests>=2.28.0
Requires-Dist: ttkbootstrap>=1.10.0
Requires-Dist: yt-dlp>=2023.3.4
Requires-Dist: mutagen>=1.46.0
Requires-Dist: plyer>=2.1.0
Requires-Dist: spotipy>=2.23.0
Requires-Dist: watchdog>=2.3.1
Requires-Dist: pillow>=9.5.0
Requires-Dist: matplotlib>=3.5.0
Requires-Dist: beautifulsoup4>=4.12.0
Requires-Dist: lxml>=4.9.0
